pytest_memray/__init__.py
pytest_memray/_version.py
pytest_memray/marks.py
pytest_memray/plugin.py
pytest_memray/py.typed
pytest_memray/utils.py
pytest_memray-1.8.0.dist-info/METADATA
pytest_memray-1.8.0.dist-info/WHEEL
pytest_memray-1.8.0.dist-info/entry_points.txt
pytest_memray-1.8.0.dist-info/licenses/LICENSE
pytest_memray-1.8.0.dist-info/RECORD
