Metadata-Version: 2.4
Name: pytest-memray
Version: 1.8.0
Summary: A simple plugin to use with pytest
Project-URL: Bug Tracker, https://github.com/bloomberg/pytest-memray/issues
Project-URL: Documentation, https://pytest-memray.readthedocs.io
Project-URL: Source Code, https://github.com/bloomberg/pytest-memray
Author-email: Pablo Galindo Salgado <pgalindo3@bloomberg.net>
Maintainer-email: Pablo Galindo Salgado <pgalindo3@bloomberg.net>
License-Expression: Apache-2.0
License-File: LICENSE
Classifier: Intended Audience :: Developers
Classifier: License :: OSI Approved :: Apache Software License
Classifier: Operating System :: POSIX :: Linux
Classifier: Programming Language :: Python :: 3.8
Classifier: Programming Language :: Python :: 3.9
Classifier: Programming Language :: Python :: 3.10
Classifier: Programming Language :: Python :: 3.11
Classifier: Programming Language :: Python :: 3.12
Classifier: Programming Language :: Python :: 3.13
Classifier: Programming Language :: Python :: 3.14
Classifier: Programming Language :: Python :: Implementation :: CPython
Classifier: Topic :: Software Development :: Debuggers
Requires-Python: >=3.8
Requires-Dist: memray>=1.12
Requires-Dist: pytest>=7.2
Provides-Extra: docs
Requires-Dist: furo>=2022.12.7; extra == 'docs'
Requires-Dist: sphinx-argparse>=0.4; extra == 'docs'
Requires-Dist: sphinx-inline-tabs>=2022.1.2b11; extra == 'docs'
Requires-Dist: sphinx>=6.1.3; extra == 'docs'
Requires-Dist: sphinxcontrib-programoutput>=0.17; extra == 'docs'
Requires-Dist: towncrier>=22.12; extra == 'docs'
Provides-Extra: lint
Requires-Dist: black==25.1.0; extra == 'lint'
Requires-Dist: isort==6.0.1; extra == 'lint'
Requires-Dist: mypy==1.17.1; extra == 'lint'
Requires-Dist: ruff==0.12.7; extra == 'lint'
Provides-Extra: test
Requires-Dist: anyio>=4.4.0; extra == 'test'
Requires-Dist: covdefaults>=2.2.2; extra == 'test'
Requires-Dist: coverage>=7.0.5; extra == 'test'
Requires-Dist: flaky>=3.7; extra == 'test'
Requires-Dist: pytest-xdist>=3.1; extra == 'test'
Requires-Dist: pytest>=7.2; extra == 'test'
